raepy/__init__.py
raepy/ledbutton/__init__.py
raepy/ledbutton/ledbutton.py
raepy/ledbutton/button/__init__.py
raepy/ledbutton/button/button.py
raepy/ledbutton/led/ECG_EngZeeMod.npy
raepy/ledbutton/led/__init__.py
raepy/ledbutton/led/led.py
raepy/rack/__init__.py
raepy/rack/rack.py
raepy/radialgripper/__init__.py
raepy/radialgripper/radialgripper.py
raepy/servo/__init__.py
raepy/servo/exceptions.py
raepy/servo/servo.py
raepy/servo/LSS_Library_Python/__init__.py
raepy/servo/LSS_Library_Python/lss.py
raepy/servo/LSS_Library_Python/lss_const.py
raepy/servo/LSS_Library_Python/test.py
raepy/utils/__init__.py
raepy/utils/singleton.py
raepy/vacmod/__init__.py
raepy/vacmod/vacmod
raepy/vacmod/vacuummodule.py
raepy-0.0.31.dist-info/LICENSE
raepy-0.0.31.dist-info/METADATA
raepy-0.0.31.dist-info/WHEEL
raepy-0.0.31.dist-info/top_level.txt
raepy-0.0.31.dist-info/RECORD
